{
    "hosP_NAME": "全德中醫診所",
    "hosP_CNT_TYPE": "基層醫療單位",
    "hosptel": "02-23682482",
    "hosP_ADDR": "臺北市大安區羅斯福路３段３７號３樓",
    "hosP_ID": "3801022978",
    "areA_TEL": null,
    "firsT_AID_LEVEL": null,
    "hosP_ALLIANCE": [
        {
            "hosP_ID": "RA10111001",
            "hosP_GROUP_NAME": "三軍總醫院策略聯盟",
            "suP_HOSP_NAME": "三軍總醫院策略聯盟\/三軍總醫院附設民眾診療服務處"
        }
    ],
    "nonE_OBS": "無障礙通路、提供無障礙廁所",
    "nonE_OBS_MEMO": "",
    "srV_LIST": "門診診療",
    "funC_TYPE": "中醫一般科",
    "srV_INFO": {
        "srv_Time": [
            [
                {
                    "yn": "N",
                    "urlYN": "X",
                    "tagw": "",
                    "hospName": ""
                },
                {
                    "yn": "N",
                    "urlYN": "X",
                    "tagw": "",
                    "hospName": ""
                },
                {
                    "yn": "Y",
                    "urlYN": "X",
                    "tagw": "",
                    "hospName": ""
                },
                {
                    "yn": "Y",
                    "urlYN": "X",
                    "tagw": "",
                    "hospName": ""
                },
                {
                    "yn": "N",
                    "urlYN": "X",
                    "tagw": "",
                    "hospName": ""
                },
                {
                    "yn": "N",
                    "urlYN": "V",
                    "tagw": "61",
                    "hospName": null
                },
                {
                    "yn": "Y",
                    "urlYN": "V",
                    "tagw": "71",
                    "hospName": ""
                }
            ],
            [
                {
                    "yn": "N",
                    "urlYN": "X",
                    "tagw": "",
                    "hospName": ""
                },
                {
                    "yn": "N",
                    "urlYN": "X",
                    "tagw": "",
                    "hospName": ""
                },
                {
                    "yn": "N",
                    "urlYN": "X",
                    "tagw": "",
                    "hospName": ""
                },
                {
                    "yn": "N",
                    "urlYN": "X",
                    "tagw": "",
                    "hospName": ""
                },
                {
                    "yn": "N",
                    "urlYN": "X",
                    "tagw": "",
                    "hospName": ""
                },
                {
                    "yn": "N",
                    "urlYN": "V",
                    "tagw": "62",
                    "hospName": null
                },
                {
                    "yn": "Y",
                    "urlYN": "V",
                    "tagw": "72",
                    "hospName": ""
                }
            ],
            [
                {
                    "yn": "Y",
                    "urlYN": "X",
                    "tagw": "",
                    "hospName": ""
                },
                {
                    "yn": "N",
                    "urlYN": "X",
                    "tagw": "",
                    "hospName": ""
                },
                {
                    "yn": "N",
                    "urlYN": "X",
                    "tagw": "",
                    "hospName": ""
                },
                {
                    "yn": "N",
                    "urlYN": "X",
                    "tagw": "",
                    "hospName": ""
                },
                {
                    "yn": "N",
                    "urlYN": "X",
                    "tagw": "",
                    "hospName": ""
                },
                {
                    "yn": "Y",
                    "urlYN": "V",
                    "tagw": "63",
                    "hospName": ""
                },
                {
                    "yn": "Y",
                    "urlYN": "V",
                    "tagw": "73",
                    "hospName": ""
                }
            ]
        ],
        "srv_Date": "113\/04\/03",
        "srv_Memo": null
    },
    "phonelongholiday": [],
    "pclongholiday": [],
    "offday": "",
    "offdaystr": "",
    "plans": "中醫兒童過敏性鼻炎照護試辦計畫、中醫慢性腎臟病門診加強照護計畫、中醫提升孕產照護品質計畫、中醫癌症患者加強照護整合方案─特定癌症患者中醫門診加強照護計畫、居家醫療整合照護計畫、居家醫療整合照護計畫-居家中醫醫療服務",
    "fee": {
        "cnT_TYPE": "O",
        "regisT_FEE_NAME": "門診掛號費 150元。",
        "eM_REGIST_FEE_NAME": "急診掛號費：院所未提供資料。",
        "feE_REMARK_NAME": "醫事機構備註： - "
    },
    "hosP_PLAN": [],
    "ch_HOSP_PLAN": [],
    "hosp_dr": [],
    "dailY_BED_URL": [],
    "hosP_FLU": null,
    "chilD24": null,
    "conT_E_DATE": "-",
    "brancH_CODE": "臺北業務組",
    "hosP_QTY_URL": "https:\/\/info.nhi.gov.tw\/INAE1000\/Query3Link?HospID=3801022978",
    "hosP_TYPE_NAME": "中醫一般診所",
    "prE_SRV_LIST": "-",
    "video_data": [
        {
            "vedioy": "否",
            "codE_CNAME": "-",
            "codE_ENAME": "-",
            "memo": null
        }
    ],
    "holidaY_REMARK": "-",
    "longitude": 121.52537,
    "latitude": 25.023504
}