{
    "hosP_NAME": "臺灣基督教門諾會醫療財團法人門諾醫院壽豐分院",
    "hosP_CNT_TYPE": "地區醫院",
    "hosptel": "03-8664600",
    "hosP_ADDR": "花蓮縣壽豐鄉共和村魚池５２號",
    "hosP_ID": "1145060029",
    "areA_TEL": null,
    "firsT_AID_LEVEL": null,
    "hosP_ALLIANCE": [
        {
            "hosP_ID": "RA60000067",
            "hosP_GROUP_NAME": "慈濟醫院Love plus團隊",
            "suP_HOSP_NAME": "慈濟醫院Love plus團隊\/佛教慈濟醫療財團法人花蓮慈濟醫院"
        },
        {
            "hosP_ID": "RA60000068",
            "hosP_GROUP_NAME": "門諾山地偏鄉整合團隊",
            "suP_HOSP_NAME": "門諾山地偏鄉整合團隊\/臺灣基督教門諾會醫療財團法人門諾醫院"
        }
    ],
    "nonE_OBS": "無障礙通路、提供不同障別溝通服務、設置無障礙服務窗口",
    "nonE_OBS_MEMO": "",
    "srV_LIST": "復健－物理治療業務、復健－職能治療業務、復健－語言治療業務、門診診療、住院診療、血液透析、精神病患者居家照護、精神科日間住院治療",
    "funC_TYPE": "家醫科、內科、精神科、復健科、中醫一般科",
    "srV_INFO": {
        "srv_Time": [
            [
                {
                    "yn": "N",
                    "urlYN": "X",
                    "tagw": "",
                    "hospName": ""
                },
                {
                    "yn": "N",
                    "urlYN": "X",
                    "tagw": "",
                    "hospName": ""
                },
                {
                    "yn": "N",
                    "urlYN": "X",
                    "tagw": "",
                    "hospName": ""
                },
                {
                    "yn": "N",
                    "urlYN": "X",
                    "tagw": "",
                    "hospName": ""
                },
                {
                    "yn": "N",
                    "urlYN": "X",
                    "tagw": "",
                    "hospName": ""
                },
                {
                    "yn": "N",
                    "urlYN": "V",
                    "tagw": "61",
                    "hospName": null
                },
                {
                    "yn": "Y",
                    "urlYN": "V",
                    "tagw": "71",
                    "hospName": ""
                }
            ],
            [
                {
                    "yn": "N",
                    "urlYN": "X",
                    "tagw": "",
                    "hospName": ""
                },
                {
                    "yn": "N",
                    "urlYN": "X",
                    "tagw": "",
                    "hospName": ""
                },
                {
                    "yn": "N",
                    "urlYN": "X",
                    "tagw": "",
                    "hospName": ""
                },
                {
                    "yn": "N",
                    "urlYN": "X",
                    "tagw": "",
                    "hospName": ""
                },
                {
                    "yn": "N",
                    "urlYN": "X",
                    "tagw": "",
                    "hospName": ""
                },
                {
                    "yn": "Y",
                    "urlYN": "V",
                    "tagw": "62",
                    "hospName": ""
                },
                {
                    "yn": "Y",
                    "urlYN": "V",
                    "tagw": "72",
                    "hospName": ""
                }
            ],
            [
                {
                    "yn": "Y",
                    "urlYN": "X",
                    "tagw": "",
                    "hospName": ""
                },
                {
                    "yn": "Y",
                    "urlYN": "X",
                    "tagw": "",
                    "hospName": ""
                },
                {
                    "yn": "Y",
                    "urlYN": "X",
                    "tagw": "",
                    "hospName": ""
                },
                {
                    "yn": "Y",
                    "urlYN": "X",
                    "tagw": "",
                    "hospName": ""
                },
                {
                    "yn": "Y",
                    "urlYN": "X",
                    "tagw": "",
                    "hospName": ""
                },
                {
                    "yn": "Y",
                    "urlYN": "V",
                    "tagw": "63",
                    "hospName": ""
                },
                {
                    "yn": "Y",
                    "urlYN": "V",
                    "tagw": "73",
                    "hospName": ""
                }
            ]
        ],
        "srv_Date": "113\/05\/01",
        "srv_Memo": "精神科急診24小時服務，非精神科無急診服務。星期六門診服務時間為每月第二週與第四週。"
    },
    "phonelongholiday": [],
    "pclongholiday": [],
    "offday": "113\/05\/04、113\/05\/18、113\/06\/01、113\/06\/15、113\/06\/29",
    "offdaystr": "113-05-04、113-05-18、113-06-01、113-06-15、113-06-29",
    "plans": "B、C肝個案追蹤醫療給付改善方案、C型肝炎全口服新藥健保給付執行計畫、中醫慢性腎臟病門診加強照護計畫、中醫癌症患者加強照護整合方案─癌症患者西醫住院中醫輔助醫療計畫、孕婦乙型鏈球菌篩檢補助服務方案、居家醫療整合照護計畫、思覺失調症醫療給付改善方案、慢性腎衰竭病人門診透析服務品質提升獎勵計畫、提升醫院用藥安全與品質方案、牙周病統合治療方案、牙醫門診加強感染管制實施方案、牙醫門診總額特殊醫療服務計畫、精神疾病嚴重病人強制住院醫療機構、糖尿病及初期慢性腎臟病照護整合方案─糖尿病、西醫住院病患中醫特定疾病輔助醫療計畫、視訊診療、醫療資源缺乏地區條件施行區域-減收20%部分",
    "fee": {
        "cnT_TYPE": "O",
        "regisT_FEE_NAME": "門診掛號費 100元。",
        "eM_REGIST_FEE_NAME": "急診掛號費 200元。",
        "feE_REMARK_NAME": "醫事機構備註：精神科急診24小時服務，非精神科無急診服務。"
    },
    "hosP_PLAN": [],
    "ch_HOSP_PLAN": [],
    "hosp_dr": [],
    "dailY_BED_URL": [
        {
            "hosP_ID": "1145060029",
            "hosP_REG": "X",
            "beD_LINK": "請點選",
            "beD_HTTP": "http:\/\/www.mch.org.tw\/Docs\/564\/Default.aspx"
        }
    ],
    "hosP_FLU": "是",
    "chilD24": null,
    "conT_E_DATE": "-",
    "brancH_CODE": "東區業務組",
    "hosP_QTY_URL": "https:\/\/info.nhi.gov.tw\/INAE1000\/Query3Link?HospID=1145060029",
    "hosP_TYPE_NAME": "精神科醫院",
    "prE_SRV_LIST": "兒童預防保健、成人預防保健、婦女子宮頸抹片檢查、孕婦產檢、兒童牙齒預防保健、口腔黏膜檢查、定量免疫法糞便潛血檢查",
    "video_data": [
        {
            "vedioy": "是",
            "codE_CNAME": "03-8664648",
            "codE_ENAME": "提供兒童快篩陽性確診評估與相關藥物開立",
            "memo": null
        }
    ],
    "holidaY_REMARK": "-",
    "longitude": 121.524925,
    "latitude": 23.870005
}