{
    "hosP_NAME": "何耳鼻喉科診所",
    "hosP_CNT_TYPE": "基層醫療單位",
    "hosptel": "04-26221366",
    "hosP_ADDR": "臺中市清水區清水里中山路１９９之１，１９９之２號",
    "hosP_ID": "3536040411",
    "areA_TEL": "0919-090385",
    "firsT_AID_LEVEL": null,
    "hosP_ALLIANCE": [
        {
            "hosP_ID": "RA30000012",
            "hosP_GROUP_NAME": "光田綜合醫院合作聯盟",
            "suP_HOSP_NAME": "光田綜合醫院合作聯盟\/光田醫療社團法人光田綜合醫院"
        }
    ],
    "nonE_OBS": "無障礙通路、提供無障礙廁所",
    "nonE_OBS_MEMO": "",
    "srV_LIST": "門診診療",
    "funC_TYPE": "耳鼻喉科",
    "plans": "家庭醫師整合性照護計畫、視訊診療",
    "fee": {
        "cnT_TYPE": "O",
        "regisT_FEE_NAME": "門診掛號費 150元。",
        "eM_REGIST_FEE_NAME": "急診掛號費：院所未提供資料。",
        "feE_REMARK_NAME": "醫事機構備註： - ",
        "regisT_URL_NAME": "-"
    },
    "dailY_BED_URL": [],
    "hosP_FLU": "是",
    "chilD24": null,
    "conT_E_DATE": "-",
    "brancH_CODE": "中區業務組",
    "hosP_QTY_URL": "https:\/\/info.nhi.gov.tw\/INAE1000\/Query3Link?HospID=3536040411",
    "hosP_TYPE_NAME": "一般診所（醫務室）",
    "prE_SRV_LIST": "成人預防保健、口腔黏膜檢查",
    "longitude": 120.57473,
    "latitude": 24.26769
}