{
    "hosP_NAME": "青年診所",
    "hosP_CNT_TYPE": "基層醫療單位",
    "hosptel": "07-7103318",
    "hosP_ADDR": "高雄市鳳山區青年路二段１６８號１－２樓",
    "hosP_ID": "3507010945",
    "areA_TEL": "0975369229",
    "firsT_AID_LEVEL": null,
    "hosP_ALLIANCE": [],
    "nonE_OBS": "-",
    "nonE_OBS_MEMO": "（無相關資料）",
    "srV_LIST": "門診診療",
    "funC_TYPE": "內科",
    "plans": "家庭醫師整合性照護計畫",
    "fee": {
        "cnT_TYPE": "O",
        "regisT_FEE_NAME": "門診掛號費 100元。",
        "eM_REGIST_FEE_NAME": "急診掛號費：院所未提供資料。",
        "feE_REMARK_NAME": "醫事機構備註： - ",
        "regisT_URL_NAME": "-"
    },
    "dailY_BED_URL": [],
    "hosP_FLU": "是",
    "chilD24": null,
    "conT_E_DATE": "-",
    "brancH_CODE": "高屏業務組",
    "hosP_QTY_URL": "https:\/\/info.nhi.gov.tw\/INAE1000\/Query3Link?HospID=3507010945",
    "hosP_TYPE_NAME": "西醫診所",
    "prE_SRV_LIST": "成人預防保健、定量免疫法糞便潛血檢查",
    "longitude": 120.350586,
    "latitude": 22.636393
}