{
    "hosP_NAME": "漢芳中醫診所",
    "hosP_CNT_TYPE": "基層醫療單位",
    "hosptel": "07-3971818",
    "hosP_ADDR": "高雄市三民區建工路４８１號１樓",
    "hosP_ID": "3807320175",
    "areA_TEL": null,
    "firsT_AID_LEVEL": null,
    "hosP_ALLIANCE": [],
    "nonE_OBS": "無障礙通路",
    "nonE_OBS_MEMO": "",
    "srV_LIST": "門診診療",
    "funC_TYPE": "中醫一般科",
    "plans": "中醫兒童過敏性鼻炎照護試辦計畫、中醫慢性腎臟病門診加強照護計畫、中醫提升孕產照護品質計畫、中醫癌症患者加強照護整合方案─特定癌症患者中醫門診加強照護計畫",
    "fee": {
        "cnT_TYPE": "O",
        "regisT_FEE_NAME": "門診掛號費 100元。",
        "eM_REGIST_FEE_NAME": "急診掛號費：院所未提供資料。",
        "feE_REMARK_NAME": "醫事機構備註： - ",
        "regisT_URL_NAME": "-"
    },
    "dailY_BED_URL": [],
    "hosP_FLU": null,
    "chilD24": null,
    "conT_E_DATE": "-",
    "brancH_CODE": "高屏業務組",
    "hosP_QTY_URL": "https:\/\/info.nhi.gov.tw\/INAE1000\/Query3Link?HospID=3807320175",
    "hosP_TYPE_NAME": "中醫一般診所",
    "prE_SRV_LIST": "-",
    "longitude": 120.32306,
    "latitude": 22.649002
}