{
    "hosP_NAME": "家佳診所",
    "hosP_CNT_TYPE": "基層醫療單位",
    "hosptel": "07-2234383",
    "hosP_ADDR": "高雄市新興區和平一路１９３號一、二樓",
    "hosP_ID": "3502062976",
    "areA_TEL": "07-2138404",
    "firsT_AID_LEVEL": null,
    "hosP_ALLIANCE": [
        {
            "hosP_ID": "RA50000063",
            "hosP_GROUP_NAME": "大同_分級醫療雙向轉診合作團隊",
            "suP_HOSP_NAME": "大同_分級醫療雙向轉診合作團隊\/高雄市立大同醫院（委託財團法人私立高雄醫學大學經營)"
        },
        {
            "hosP_ID": "RA50000070",
            "hosP_GROUP_NAME": "高醫_分級醫療雙向轉診共同照護討",
            "suP_HOSP_NAME": "高醫_分級醫療雙向轉診共同照護討\/財團法人私立高雄醫學大學附設中和紀念醫院"
        }
    ],
    "nonE_OBS": "無障礙通路、提供不同障別溝通服務",
    "nonE_OBS_MEMO": "",
    "srV_LIST": "門診診療",
    "funC_TYPE": "家醫科",
    "srV_INFO": {
        "srv_Time": [
            [
                {
                    "yn": "N",
                    "urlYN": "X",
                    "tagw": "",
                    "hospName": ""
                },
                {
                    "yn": "N",
                    "urlYN": "X",
                    "tagw": "",
                    "hospName": ""
                },
                {
                    "yn": "N",
                    "urlYN": "X",
                    "tagw": "",
                    "hospName": ""
                },
                {
                    "yn": "N",
                    "urlYN": "X",
                    "tagw": "",
                    "hospName": ""
                },
                {
                    "yn": "N",
                    "urlYN": "X",
                    "tagw": "",
                    "hospName": ""
                },
                {
                    "yn": "N",
                    "urlYN": "V",
                    "tagw": "61",
                    "hospName": null
                },
                {
                    "yn": "Y",
                    "urlYN": "V",
                    "tagw": "71",
                    "hospName": ""
                }
            ],
            [
                {
                    "yn": "N",
                    "urlYN": "X",
                    "tagw": "",
                    "hospName": ""
                },
                {
                    "yn": "N",
                    "urlYN": "X",
                    "tagw": "",
                    "hospName": ""
                },
                {
                    "yn": "N",
                    "urlYN": "X",
                    "tagw": "",
                    "hospName": ""
                },
                {
                    "yn": "N",
                    "urlYN": "X",
                    "tagw": "",
                    "hospName": ""
                },
                {
                    "yn": "N",
                    "urlYN": "X",
                    "tagw": "",
                    "hospName": ""
                },
                {
                    "yn": "Y",
                    "urlYN": "V",
                    "tagw": "62",
                    "hospName": ""
                },
                {
                    "yn": "Y",
                    "urlYN": "V",
                    "tagw": "72",
                    "hospName": ""
                }
            ],
            [
                {
                    "yn": "N",
                    "urlYN": "X",
                    "tagw": "",
                    "hospName": ""
                },
                {
                    "yn": "N",
                    "urlYN": "X",
                    "tagw": "",
                    "hospName": ""
                },
                {
                    "yn": "N",
                    "urlYN": "X",
                    "tagw": "",
                    "hospName": ""
                },
                {
                    "yn": "N",
                    "urlYN": "X",
                    "tagw": "",
                    "hospName": ""
                },
                {
                    "yn": "N",
                    "urlYN": "X",
                    "tagw": "",
                    "hospName": ""
                },
                {
                    "yn": "Y",
                    "urlYN": "V",
                    "tagw": "63",
                    "hospName": ""
                },
                {
                    "yn": "Y",
                    "urlYN": "V",
                    "tagw": "73",
                    "hospName": ""
                }
            ]
        ],
        "srv_Date": "113\/05\/01",
        "srv_Memo": null
    },
    "phonelongholiday": [],
    "pclongholiday": [],
    "offday": "",
    "offdaystr": "",
    "plans": "全民健康保險代謝症候群防治計畫、家庭醫師整合性照護計畫、居家醫療整合照護計畫、氣喘醫療給付改善方案、糖尿病及初期慢性腎臟病照護整合方案─初期慢性腎臟病",
    "fee": {
        "cnT_TYPE": "O",
        "regisT_FEE_NAME": "門診掛號費 150元。",
        "eM_REGIST_FEE_NAME": "急診掛號費 250元。",
        "feE_REMARK_NAME": "醫事機構備註：初診及高師大師生掛號費優惠收100元(不含部分負擔)"
    },
    "hosP_PLAN": [],
    "ch_HOSP_PLAN": [],
    "hosp_dr": [],
    "dailY_BED_URL": [],
    "hosP_FLU": "是",
    "chilD24": null,
    "conT_E_DATE": "-",
    "brancH_CODE": "高屏業務組",
    "hosP_QTY_URL": "https:\/\/info.nhi.gov.tw\/INAE1000\/Query3Link?HospID=3502062976",
    "hosP_TYPE_NAME": "專科診所",
    "prE_SRV_LIST": "兒童預防保健、成人預防保健、口腔黏膜檢查、定量免疫法糞便潛血檢查",
    "video_data": [
        {
            "vedioy": "否",
            "codE_CNAME": "-",
            "codE_ENAME": "-",
            "memo": null
        }
    ],
    "holidaY_REMARK": "6月10日端午節休診1日"
}